mquery_query_lib/__init__.py
mquery_query_lib/yaraparse.py
mquery_query_lib-0.0.1.dist-info/METADATA
mquery_query_lib-0.0.1.dist-info/WHEEL
mquery_query_lib-0.0.1.dist-info/top_level.txt
mquery_query_lib-0.0.1.dist-info/RECORD
